django_thumbs/__init__.py
django_thumbs/fields.py
django_thumbs/models.py
django_thumbs/tests.py
django_thumbs_v2-0.4.1.dist-info/DESCRIPTION.rst
django_thumbs_v2-0.4.1.dist-info/METADATA
django_thumbs_v2-0.4.1.dist-info/RECORD
django_thumbs_v2-0.4.1.dist-info/WHEEL
django_thumbs_v2-0.4.1.dist-info/metadata.json
django_thumbs_v2-0.4.1.dist-info/top_level.txt
