Metadata-Version: 1.1
Name: django-thumbs-v2
Version: 0.4.1
Summary: The easiest way to create thumbnails for your images with Django. Works with any storage backend.
Home-page: https://github.com/rrmerugu/django-thumbs
Author: Ravi Raja Merugu
Author-email: rrmerugu@gmail.com
License: UNKNOWN
Platform: UNKNOWN
Classifier: Development Status :: 4 - Beta
Classifier: Intended Audience :: Developers
Classifier: License :: OSI Approved :: BSD License
Classifier: Operating System :: OS Independent
Classifier: Programming Language :: Python
